setup.py
distri_probability/Binomialdistribution.py
distri_probability/Gaussiandistribution.py
distri_probability/Generaldistribution.py
distri_probability/__init__.py
distri_probability.egg-info/PKG-INFO
distri_probability.egg-info/SOURCES.txt
distri_probability.egg-info/dependency_links.txt
distri_probability.egg-info/not-zip-safe
distri_probability.egg-info/top_level.txt