Metadata-Version: 1.0
Name: distri-probability
Version: 1.0
Summary: Gaussian and Binomial distributions
Home-page: UNKNOWN
Author: Akandji Mujibu
Author-email: makandjibeni@gmail.com
License: UNKNOWN
Platform: UNKNOWN
